LICENSE.txt
README.md
setup.cfg
setup.py
src/qtt/__init__.py
src/qtt/data.py
src/qtt/dataset_processing.py
src/qtt/exceptions.py
src/qtt/pgeometry.py
src/qtt/structures.py
src/qtt/version.py
src/qtt.egg-info/PKG-INFO
src/qtt.egg-info/SOURCES.txt
src/qtt.egg-info/dependency_links.txt
src/qtt.egg-info/not-zip-safe
src/qtt.egg-info/requires.txt
src/qtt.egg-info/top_level.txt
src/qtt/algorithms/__init__.py
src/qtt/algorithms/allxy.py
src/qtt/algorithms/anticrossing.py
src/qtt/algorithms/awg_to_plunger.py
src/qtt/algorithms/bias_triangles.py
src/qtt/algorithms/chargesensor.py
src/qtt/algorithms/coulomb.py
src/qtt/algorithms/fitting.py
src/qtt/algorithms/functions.py
src/qtt/algorithms/gatesweep.py
src/qtt/algorithms/generic.py
src/qtt/algorithms/images.py
src/qtt/algorithms/markov_chain.py
src/qtt/algorithms/misc.py
src/qtt/algorithms/ohmic.py
src/qtt/algorithms/onedot.py
src/qtt/algorithms/pat_fitting.py
src/qtt/algorithms/random_telegraph_signal.py
src/qtt/algorithms/tunneling.py
src/qtt/exampledata/double_gaussian_dataset.json
src/qtt/exampledata/elzerman_detuning_scan.json
src/qtt/exampledata/frequency_rabi_scan.json
src/qtt/exampledata/time_rabi_scan.json
src/qtt/exampledata/videomode_1d_printscreen.png
src/qtt/exampledata/videomode_2d_printscreen.png
src/qtt/exampledata/2electron_pat/background/snapshot.json
src/qtt/exampledata/2electron_pat/background/sweepparam.dat
src/qtt/exampledata/2electron_pat/pat/mwsource_frequency_sweepparam.dat
src/qtt/exampledata/2electron_pat/pat/snapshot.json
src/qtt/exampledata/PAT_scan/mwsource_frequency_sweepparam.dat
src/qtt/exampledata/PAT_scan/snapshot.json
src/qtt/exampledata/PAT_scan_background/snapshot.json
src/qtt/exampledata/PAT_scan_background/sweepparam.dat
src/qtt/exampledata/addition_line_scan/gates_P4_set.dat
src/qtt/exampledata/addition_line_scan/snapshot.json
src/qtt/exampledata/charge_stability_diagram_anti_crossing/charge_stability_diagram_anti_crossing.hdf5
src/qtt/exampledata/charge_stability_diagram_anti_crossing_virtual_gates/snapshot.json
src/qtt/exampledata/charge_stability_diagram_anti_crossing_virtual_gates/stepparam_sweepparam.dat
